obs_tally_luxafor/__init__.py
obs_tally_luxafor/cli.py
obs_tally_luxafor/client.py
obs_tally_luxafor-0.3.1.dist-info/METADATA
obs_tally_luxafor-0.3.1.dist-info/WHEEL
obs_tally_luxafor-0.3.1.dist-info/entry_points.txt
obs_tally_luxafor-0.3.1.dist-info/top_level.txt
obs_tally_luxafor-0.3.1.dist-info/RECORD
