Metadata-Version: 2.2
Name: obs-tally-luxafor
Version: 0.3.1
Summary: OBS integration with Luxafor LED devices
Home-page: https://github.com/nahakiole/obs-tally-luxafor
Author: Robin Glauser
Author-email: robin.glauser@gmail.com
Classifier: Programming Language :: Python :: 3
Classifier: Operating System :: OS Independent
Requires-Python: >=3.6
Requires-Dist: requests
Requires-Dist: obsws_python
Dynamic: author
Dynamic: author-email
Dynamic: classifier
Dynamic: description
Dynamic: description-content-type
Dynamic: home-page
Dynamic: requires-dist
Dynamic: requires-python
Dynamic: summary
